setup.py
PlantLidar/__init__.py
PlantLidar/gps.py
PlantLidar/io.py
PlantLidar/preprocessing.py
PlantLidar/processing.py
PlantLidar/searching.py
PlantLidar/utils.py
PlantLidar/visualization.py
PlantLidar.egg-info/PKG-INFO
PlantLidar.egg-info/SOURCES.txt
PlantLidar.egg-info/dependency_links.txt
PlantLidar.egg-info/requires.txt
PlantLidar.egg-info/top_level.txt
PlantLidar/CoordinateTransform/__init__.py
PlantLidar/CoordinateTransform/converGPS.py
PlantLidar/CoordinateTransform/mix.py
PlantLidar/Cplus_methods/__init__.py
PlantLidar/Cplus_methods/test.py